forgequerystats/__init__.py
forgequerystats/core.py
forgequerystats/middleware.py
forgequerystats/sql.py
forgequerystats/templates/querystats/button.html
forgequerystats/templates/querystats/querystats.html
forgequerystats/templates/querystats/stafftoolbar.html
forge_querystats-0.3.0.dist-info/METADATA
forge_querystats-0.3.0.dist-info/WHEEL
forge_querystats-0.3.0.dist-info/RECORD
